pyfastg/__init__.py
pyfastg/pyfastg.py
pyfastg/tests/__init__.py
pyfastg/tests/test_add_node.py
pyfastg/tests/test_extract_node_attrs.py
pyfastg/tests/test_parse.py
pyfastg/tests/test_validate_seq_and_compute_gc.py
pyfastg-0.2.0.dist-info/licenses/LICENSE
pyfastg-0.2.0.dist-info/METADATA
pyfastg-0.2.0.dist-info/WHEEL
pyfastg-0.2.0.dist-info/top_level.txt
pyfastg-0.2.0.dist-info/RECORD
